polynomial_regression/__init__.py
polynomial_regression/polyregress.py
polynomial_regression-0.0.2.dist-info/LICENSE
polynomial_regression-0.0.2.dist-info/METADATA
polynomial_regression-0.0.2.dist-info/WHEEL
polynomial_regression-0.0.2.dist-info/top_level.txt
polynomial_regression-0.0.2.dist-info/RECORD
