Metadata-Version: 2.1
Name: polynomial-regression
Version: 0.0.2
Summary: Polynomial Regression for points in X-Y Plane
Home-page: https://github.com/the-krushnakant/polynomial-regression
Author: Krushnakant Bhattad
Author-email: krushnakant@cse.iitb.ac.in
License: UNKNOWN
Platform: UNKNOWN
Classifier: Programming Language :: Python :: 3
Classifier: License :: OSI Approved :: MIT License
Classifier: Operating System :: OS Independent
Requires-Python: >=3.6
Requires-Dist: numpy
